worldai/__init__.py
worldai-0.1.0.dist-info/METADATA
worldai-0.1.0.dist-info/WHEEL
worldai-0.1.0.dist-info/top_level.txt
worldai-0.1.0.dist-info/RECORD
