Metadata-Version: 2.4
Name: worldai
Version: 0.1.0
Summary: Core WorldAI Python package
Author-email: WorldAI <info@example.com>
License-Expression: MIT
Keywords: worldai,ai
Requires-Python: >=3.8
